integral_flask_project/__init__.py
integral_flask_project/import_moduls.py
integral_flask_project/integral_project.py
src_IFP/__init__.py
src_IFP/config/__init__.py
src_IFP/config/app.py
src_IFP/config/config.py
src_IFP/config/cors_config.py
src_IFP/config/database_config.py
src_IFP/config/cors/__init__.py
src_IFP/config/cors/cors.py
src_IFP/test/__init__.py
src_IFP/test/test_app_config.py
src_IFP/test/test_config.py
src_IFP/test/test_cors_manager.py
src_IFP/test/test_flask_project.py
src_IFP/test/test_module_importer.py
Integral_flask_project-0.0.3.dist-info/METADATA
Integral_flask_project-0.0.3.dist-info/WHEEL
Integral_flask_project-0.0.3.dist-info/top_level.txt
Integral_flask_project-0.0.3.dist-info/RECORD
