Metadata-Version: 2.1
Name: Integral-flask-project
Version: 0.0.3
Summary: A powerful Flask extension that provides an integrated solution for building robust web applications with WebSocket support, JWT authentication, database management, email handling, and CORS configuration.
Home-page: https://github.com/ConectarWali/Integral-flask-project
Author: Conectar Wali SAS
Author-email: dev@conectarwalisas.com.co
Classifier: Programming Language :: Python :: 3
Classifier: License :: OSI Approved :: MIT License
Classifier: Operating System :: OS Independent
Requires-Python: >=3.7
Requires-Dist: alembic==1.14.0
Requires-Dist: bidict==0.23.1
Requires-Dist: blinker==1.9.0
Requires-Dist: click==8.1.8
Requires-Dist: colorama==0.4.6
Requires-Dist: Flask==3.1.0
Requires-Dist: Flask-Cors==5.0.0
Requires-Dist: Flask-JWT-Extended==4.7.1
Requires-Dist: Flask-Mail==0.10.0
Requires-Dist: Flask-Migrate==4.0.7
Requires-Dist: Flask-SocketIO==5.5.0
Requires-Dist: Flask-SQLAlchemy==3.1.1
Requires-Dist: greenlet==3.1.1
Requires-Dist: h11==0.14.0
Requires-Dist: itsdangerous==2.2.0
Requires-Dist: Jinja2==3.1.5
Requires-Dist: Mako==1.3.8
Requires-Dist: MarkupSafe==3.0.2
Requires-Dist: PyJWT==2.10.1
Requires-Dist: PyMySQL==1.1.1
Requires-Dist: python-dotenv==1.0.1
Requires-Dist: python-engineio==4.11.2
Requires-Dist: python-socketio==5.12.1
Requires-Dist: redis==5.2.1
Requires-Dist: simple-websocket==1.1.0
Requires-Dist: SQLAlchemy==2.0.36
Requires-Dist: SQLAlchemy-Utils==0.41.2
Requires-Dist: typing-extensions==4.12.2
Requires-Dist: Werkzeug==3.1.3
Requires-Dist: wsproto==1.2.0
